conformity/__init__.py
conformity/conformity.py
node_conformity-0.0.2.dist-info/LICENSE
node_conformity-0.0.2.dist-info/METADATA
node_conformity-0.0.2.dist-info/WHEEL
node_conformity-0.0.2.dist-info/top_level.txt
node_conformity-0.0.2.dist-info/RECORD
